{
  "headers": {
    "date": "Thu, 07 Jul 2022 07:46:50 GMT",
    "cache-control": "public, max-age=31536000, immutable",
    "x-amz-request-id": "MFX7564FBQGJ5188",
    "content-type": "application/typescript; charset=utf-8",
    "x-amz-version-id": "o31n3tn_BUPnqikRwRfEQAA6luTnCKHG",
    "access-control-allow-origin": "*",
    "content-length": "800",
    "server": "deno/asia-southeast1-a",
    "last-modified": "Thu, 03 Mar 2022 15:20:12 GMT",
    "vary": "Accept-Encoding",
    "x-amz-id-2": "9fq4SRD30NA9PsFEkFz38xlodxbfj0f5qpkSOKBUKNkZpJVlQKSN4aM2Xu1dw7qyDusHvatJ4qY=",
    "etag": "\"08f89a7f3c97fea64130e79ae4b3aea9\""
  },
  "url": "https://deno.land/std@0.128.0/path/mod.ts",
  "now": {
    "secs_since_epoch": 1657180010,
    "nanos_since_epoch": 174808439
  }
}